setup.py
jjb_separator_param/__init__.py
jjb_separator_param/separator_param.py
jjb_separator_param.egg-info/PKG-INFO
jjb_separator_param.egg-info/SOURCES.txt
jjb_separator_param.egg-info/dependency_links.txt
jjb_separator_param.egg-info/entry_points.txt
jjb_separator_param.egg-info/requires.txt
jjb_separator_param.egg-info/top_level.txt