Metadata-Version: 1.1
Name: jjb-separator-param
Version: 0.1.0
Summary: Jenkins Job Builder Separator Param
Home-page: https://github.com/ochirkov/jenkins-job-builder-separator-parameter
Author: Chyrkov Oleksandr
Author-email: ironloriin20@gmail.com
License: Apache-2.0 license
Platform: UNKNOWN
Classifier: Environment :: Console
Classifier: Intended Audience :: Developers
Classifier: Intended Audience :: Information Technology
Classifier: License :: OSI Approved :: Apache Software License
Classifier: Operating System :: OS Independent
Classifier: Programming Language :: Python
Classifier: Programming Language :: Python :: 2
Classifier: Programming Language :: Python :: 3
